connectivator/__init__.py
connectivator/gsheets.py
connectivator/postgres.py
connectivator/transfer.py
connectivator-0.0.7.dist-info/LICENSE
connectivator-0.0.7.dist-info/METADATA
connectivator-0.0.7.dist-info/WHEEL
connectivator-0.0.7.dist-info/top_level.txt
connectivator-0.0.7.dist-info/RECORD
