Metadata-Version: 2.1
Name: connectivator
Version: 0.0.7
Summary: Simple wrapper functions for connecting to and loading data
Home-page: https://github.com/jonathan-marsan/connectivator
Author: Jonathan
License: UNKNOWN
Platform: UNKNOWN
Classifier: Programming Language :: Python :: 3
Classifier: License :: OSI Approved :: MIT License
Classifier: Operating System :: OS Independent
Requires-Dist: pandas
Requires-Dist: SQLAlchemy
Requires-Dist: psycopg2
Requires-Dist: gspread
Requires-Dist: gspread-dataframe
Requires-Dist: oauth2client
